evm_asm/__init__.py
evm_asm/assembler.py
evm_asm/errors.py
evm_asm/py.typed
evm_asm/typing.py
evm_asm/version.py
evm_asm/forks/__init__.py
evm_asm/forks/base.py
evm_asm/forks/byzantium.py
evm_asm/forks/constantinople.py
evm_asm/forks/frontier.py
evm_asm/forks/homestead.py
evm_asm/forks/istanbul.py
evm_asm/forks/muir_glacier.py
evm_asm/forks/petersburg.py
evm_asm/forks/spurious_dragon.py
evm_asm/forks/tangerine_whistle.py
evm_asm-0.1.0a0.dist-info/LICENSE
evm_asm-0.1.0a0.dist-info/METADATA
evm_asm-0.1.0a0.dist-info/WHEEL
evm_asm-0.1.0a0.dist-info/top_level.txt
evm_asm-0.1.0a0.dist-info/RECORD
