Metadata-Version: 2.1
Name: evm-asm
Version: 0.1.0a0
Summary: UNKNOWN
Home-page: https://github.com/ApeWorX/evm-asm
Author: Shade Undertree
Author-email: shadeundertree@gmail.com
License: Apache-2.0
Keywords: ethereum
Platform: UNKNOWN
Classifier: Development Status :: 3 - Alpha
Classifier: Intended Audience :: Developers
Classifier: License :: OSI Approved :: Apache Software License
Classifier: Natural Language :: English
Classifier: Operating System :: MacOS
Classifier: Operating System :: POSIX
Classifier: Programming Language :: Python :: 3
Classifier: Programming Language :: Python :: 3.6
Classifier: Programming Language :: Python :: 3.7
Classifier: Programming Language :: Python :: 3.8
Classifier: Programming Language :: Python :: 3.9
Requires-Python: >=3.6, <4
Provides-Extra: dev
Requires-Dist: pytest (<7.0,>=6.0) ; extra == 'dev'
Requires-Dist: pytest-xdist ; extra == 'dev'
Requires-Dist: pytest-cov ; extra == 'dev'
Requires-Dist: py-evm (==0.3.0a20) ; extra == 'dev'
Requires-Dist: web3 (<6.0) ; extra == 'dev'
Requires-Dist: black (<21.0,>=20.8b1) ; extra == 'dev'
Requires-Dist: mypy (<1.0,>=0.800) ; extra == 'dev'
Requires-Dist: flake8 (<4.0,>=3.8.3) ; extra == 'dev'
Requires-Dist: isort (<6.0,>=5.7.0) ; extra == 'dev'
Requires-Dist: Sphinx (<4,>=3.4.3) ; extra == 'dev'
Requires-Dist: sphinx-rtd-theme (<1,>=0.1.9) ; extra == 'dev'
Requires-Dist: towncrier (<20,>=19.2.0) ; extra == 'dev'
Requires-Dist: flask ; extra == 'dev'
Requires-Dist: flask-table ; extra == 'dev'
Requires-Dist: setuptools ; extra == 'dev'
Requires-Dist: setuptools-scm ; extra == 'dev'
Requires-Dist: wheel ; extra == 'dev'
Requires-Dist: twine ; extra == 'dev'
Requires-Dist: commitizen ; extra == 'dev'
Requires-Dist: pytest-watch ; extra == 'dev'
Requires-Dist: IPython ; extra == 'dev'
Requires-Dist: ipdb ; extra == 'dev'
Provides-Extra: doc
Requires-Dist: Sphinx (<4,>=3.4.3) ; extra == 'doc'
Requires-Dist: sphinx-rtd-theme (<1,>=0.1.9) ; extra == 'doc'
Requires-Dist: towncrier (<20,>=19.2.0) ; extra == 'doc'
Provides-Extra: ethervm
Requires-Dist: flask ; extra == 'ethervm'
Requires-Dist: flask-table ; extra == 'ethervm'
Requires-Dist: web3 (<6.0) ; extra == 'ethervm'
Provides-Extra: lint
Requires-Dist: black (<21.0,>=20.8b1) ; extra == 'lint'
Requires-Dist: mypy (<1.0,>=0.800) ; extra == 'lint'
Requires-Dist: flake8 (<4.0,>=3.8.3) ; extra == 'lint'
Requires-Dist: isort (<6.0,>=5.7.0) ; extra == 'lint'
Provides-Extra: release
Requires-Dist: setuptools ; extra == 'release'
Requires-Dist: setuptools-scm ; extra == 'release'
Requires-Dist: wheel ; extra == 'release'
Requires-Dist: twine ; extra == 'release'
Provides-Extra: test
Requires-Dist: pytest (<7.0,>=6.0) ; extra == 'test'
Requires-Dist: pytest-xdist ; extra == 'test'
Requires-Dist: pytest-cov ; extra == 'test'
Requires-Dist: py-evm (==0.3.0a20) ; extra == 'test'
Requires-Dist: web3 (<6.0) ; extra == 'test'
